{
  "argument_loc": "Global",
  "description": "",
  "effect_loc": "Local",
  "examples": [
    "<sqf>_actions = actionIDs player;</sqf>"
  ],
  "groups": [
    "Interaction"
  ],
  "id": "actionIDs",
  "name": "actionIDs",
  "problem_notes": [],
  "see_also": [
    "actionParams",
    "addAction",
    "setUserActionText",
    "inGameUISetEventHandler",
    "showHUD",
    "inputAction",
    "removeAction",
    "removeAllActions",
    "action"
  ],
  "since": {},
  "status": "Passed",
  "syntax": [
    {
      "call": {
        "Unary": "entity"
      },
      "ret": {
        "desc": "IDs of all user actions added to given entity with [[addAction]] command",
        "type": {
          "ArrayUnsized": {
            "value": "Number"
          }
        }
      },
      "right": {
        "Item": {
          "desc": "entity with added user actions",
          "name": "entity",
          "type": "Object"
        }
      }
    }
  ]
}