{
  "argument_loc": "Unspecified",
  "description": "Return a list of all dead units including agents and destroyed vehicles. Dead units may be in vehicles.",
  "effect_loc": "Unspecified",
  "examples": [
    "<sqf>{ deleteVehicle _x } forEach allDead;</sqf>",
    "allAlive:\n<sqf>\n_all = allUnits + vehicles;\n{\n\t_all pushBack agent _x;\n} forEach (agents - [teamMemberNull]);\nallAlive = _all - allDead;\n</sqf>"
  ],
  "groups": [
    "Object Detection"
  ],
  "id": "allDead",
  "name": "allDead",
  "problem_notes": [],
  "see_also": [
    "allDeadMen",
    "allUnits",
    "allGroups",
    "playableUnits",
    "switchableUnits",
    "units",
    "vehicles",
    "allCurators"
  ],
  "status": "Passed",
  "syntax": [
    {
      "call": "Nular",
      "ret": {
        "type": {
          "ArrayUnsized": {
            "value": "Object"
          }
        }
      }
    }
  ]
}