{
  "alias": [
    "[[west]]"
  ],
  "argument_loc": "Unspecified",
  "description": "Pre-defined variable for the blufor [[Side|side]].",
  "effect_loc": "Unspecified",
  "examples": [
    "<sqf>\nif (side player == blufor) then\n{\n\thint \"BLUFOR\";\n};\n</sqf>"
  ],
  "groups": [
    "Sides"
  ],
  "id": "blufor",
  "name": "blufor",
  "problem_notes": [],
  "see_also": [
    "side",
    "civilian",
    "east",
    "independent",
    "opfor",
    "resistance",
    "west"
  ],
  "since": {},
  "status": "Passed",
  "syntax": [
    {
      "call": "Nular",
      "ret": {
        "type": "Side"
      }
    }
  ]
}