{
  "argument_loc": "Global",
  "description": "Returns all items names and count from ammo box (or any general weapon holder container).",
  "effect_loc": "Unspecified",
  "examples": [
    "<sqf>\ngetItemCargo cursorTarget;\n/*\n\treturns e.g\n\t[\n        [\"5ItemA\", \"10ItemB\"]\n        [5, 10]\n\t]\n*/\n</sqf>"
  ],
  "groups": [
    "Vehicle Inventory"
  ],
  "id": "getItemCargo",
  "name": "getItemCargo",
  "problem_notes": [],
  "see_also": [
    "itemCargo",
    "addItemCargo",
    "addItemCargoGlobal",
    "clearItemCargo",
    "clearItemCargoGlobal"
  ],
  "since": {},
  "status": "Passed",
  "syntax": [
    {
      "call": {
        "Unary": "box"
      },
      "ret": {
        "type": {
          "ArraySized": [
            {
              "default": null,
              "desc": "Item class names",
              "name": "classes",
              "since": null,
              "type": {
                "ArrayUnsized": {
                  "value": "String"
                }
              }
            },
            {
              "default": null,
              "desc": "Item counts",
              "name": "counts",
              "since": null,
              "type": {
                "ArrayUnsized": {
                  "value": "Number"
                }
              }
            }
          ]
        }
      },
      "right": {
        "Item": {
          "name": "box",
          "type": "Object"
        }
      }
    }
  ]
}