{
  "argument_loc": "Unspecified",
  "description": "Return object which is sling loaded by vehicle",
  "effect_loc": "Unspecified",
  "examples": [
    "<sqf>_cargo = getSlingLoad heli1;</sqf>"
  ],
  "groups": [
    "Ropes and Sling Loading"
  ],
  "id": "getSlingLoad",
  "name": "getSlingLoad",
  "problem_notes": [],
  "see_also": [
    "ropes",
    "canSlingLoad",
    "enableRopeAttach",
    "ropeAttachedObjects",
    "ropeAttachTo",
    "ropeDestroy",
    "ropeLength",
    "ropeUnwound",
    "ropeAttachedTo",
    "ropeCreate",
    "ropeDetach",
    "ropeAttachEnabled",
    "ropeCut",
    "ropeEndPosition",
    "ropeUnwind",
    "setSlingLoad",
    "slingLoadAssistantShown"
  ],
  "status": "Passed",
  "syntax": [
    {
      "call": {
        "Unary": "vehicle"
      },
      "ret": {
        "desc": "the sling loaded vehicle. [[objNull]] if nothing is sling loaded.",
        "type": "Object"
      },
      "right": {
        "Item": {
          "name": "vehicle",
          "type": "Object"
        }
      }
    }
  ]
}