{
  "argument_loc": "Unspecified",
  "description": "Registers a new task type. Parameters are defined in the given config class (subclass of {{hl|CfgTasks}})",
  "effect_loc": "Unspecified",
  "examples": [
    "<sqf>teamMember _agent registerTask \"MyTask\";</sqf>"
  ],
  "groups": [
    "Briefing",
    "Teams"
  ],
  "name": "registerTask",
  "problem_notes": [],
  "see_also": [
    "registeredTasks",
    "unregisterTask",
    "sendTask",
    "createTask",
    "currentTasks",
    "taskCompleted"
  ],
  "status": "Passed",
  "syntax": [
    {
      "call": {
        "Binary": [
          "teamMember",
          "entryName"
        ]
      },
      "left": {
        "Item": {
          "desc": "[[teamMember]] [[agent]]",
          "name": "teamMember",
          "type": "TeamMember"
        }
      },
      "ret": {
        "desc": "[[true]] on success",
        "type": "Boolean"
      },
      "right": {
        "Item": {
          "desc": "{{hl|CfgTasks}} classname",
          "name": "entryName",
          "type": "String"
        }
      }
    }
  ]
}