{
  "argument_loc": "Global",
  "description": "Sets the name of a location or a person (person only in single player).",
  "effect_loc": "Local",
  "examples": [
    "<sqf>myLocation setName \"My Location Name\";</sqf>",
    "<sqf>player setName \"New Name\";</sqf>",
    "<sqf>player setName [\"Ben Kerry\",\"Ben\",\"Kerry\"];</sqf>"
  ],
  "groups": [
    "Unit Identity",
    "Locations"
  ],
  "id": "setName",
  "name": "setName",
  "problem_notes": [],
  "see_also": [
    "name",
    "nameSound",
    "setNameSound",
    "setIdentity"
  ],
  "status": "Passed",
  "syntax": [
    {
      "call": {
        "Binary": [
          "thing",
          "name"
        ]
      },
      "left": {
        "Item": {
          "desc": "or {{GVI|arma3|1.02|size= 0.75}} [[Object]]",
          "name": "thing",
          "type": "Location"
        }
      },
      "ret": {
        "type": "Nothing"
      },
      "right": {
        "Item": {
          "name": "name",
          "type": "String"
        }
      }
    },
    {
      "call": {
        "Binary": [
          "unit",
          [
            "name",
            "firstName",
            "lastName"
          ]
        ]
      },
      "left": {
        "Item": {
          "name": "unit",
          "type": "Object"
        }
      },
      "ret": {
        "type": "Nothing"
      },
      "right": {
        "Array": [
          {
            "Item": {
              "name": "name",
              "type": "String"
            }
          },
          {
            "Item": {
              "name": "firstName",
              "type": "String"
            }
          },
          {
            "Item": {
              "name": "lastName",
              "type": "String"
            }
          }
        ]
      },
      "since": {
        "arma3": "1.2"
      }
    }
  ]
}