{
  "argument_loc": "Unspecified",
  "description": "Sets a location's [[Side|side]]. The default side is Unknown.\n{{Feature|important|To change a ''unit'''s side, see {{Link|#Notes}}.}}",
  "effect_loc": "Unspecified",
  "examples": [
    "<sqf>_myLocation setSide resistance;</sqf>"
  ],
  "groups": [
    "Sides",
    "Locations"
  ],
  "id": "setSide",
  "name": "setSide",
  "problem_notes": [],
  "see_also": [
    "Side",
    "side",
    "west",
    "east",
    "resistance",
    "civilian",
    "sideUnknown",
    "sideFriendly",
    "sideEnemy",
    "playerSide",
    "Side",
    "Relations",
    "independent"
  ],
  "status": "Passed",
  "syntax": [
    {
      "call": {
        "Binary": [
          "location",
          "side"
        ]
      },
      "left": {
        "Item": {
          "name": "location",
          "type": "Location"
        }
      },
      "ret": {
        "type": "Nothing"
      },
      "right": {
        "Item": {
          "name": "side",
          "type": "Side"
        }
      }
    }
  ]
}