{
  "argument_loc": "Unspecified",
  "description": "Set the average gap between ambient cars in a rectangle (in meters). {{Feature|arma3|This command does nothing in {{arma3}}.}}",
  "effect_loc": "Unspecified",
  "examples": [
    "<sqf>setTrafficGap [50, 31000, 32500, 28000, 32000];</sqf>"
  ],
  "groups": [
    "Environment"
  ],
  "id": "setTrafficGap",
  "name": "setTrafficGap",
  "problem_notes": [],
  "see_also": [
    "enableTraffic",
    "setTrafficDensity",
    "setTrafficDistance",
    "setTrafficSpeed"
  ],
  "since": {},
  "status": "Passed",
  "syntax": [
    {
      "call": {
        "Unary": [
          "gap",
          "xMin",
          "xMax",
          "zMin",
          "zMax"
        ]
      },
      "ret": {
        "type": "Nothing"
      },
      "right": {
        "Array": [
          {
            "Item": {
              "desc": "average gap between ambient cars (in meters)",
              "name": "gap",
              "type": "Number"
            }
          },
          {
            "Item": {
              "desc": "western border of the affected rectangle",
              "name": "xMin",
              "type": "Number"
            }
          },
          {
            "Item": {
              "desc": "eastern border of the affected rectangle",
              "name": "xMax",
              "type": "Number"
            }
          },
          {
            "Item": {
              "desc": "southern border of the affected rectangle",
              "name": "zMin",
              "type": "Number"
            }
          },
          {
            "Item": {
              "desc": "northern border of the affected rectangle",
              "name": "zMax",
              "type": "Number"
            }
          }
        ]
      }
    }
  ]
}