{
  "argument_loc": "Unspecified",
  "description": "Sets ID to vehicle. By this ID vehicle is referenced by triggers and waypoints.\n\n{{Feature|warning|This command is '''not''' to be used.}}",
  "effect_loc": "Unspecified",
  "examples": [
    "<sqf>player setVehicleId 1;</sqf>"
  ],
  "groups": [
    "Object Manipulation",
    "Broken Commands"
  ],
  "id": "setVehicleId",
  "name": "setVehicleId",
  "problem_notes": [],
  "see_also": [
    "setVehicleVarName"
  ],
  "since": {},
  "status": "Passed",
  "syntax": [
    {
      "call": {
        "Binary": [
          "vehicleName",
          "id"
        ]
      },
      "left": {
        "Item": {
          "name": "vehicleName",
          "type": "Object"
        }
      },
      "ret": {
        "type": "Nothing"
      },
      "right": {
        "Item": {
          "name": "id",
          "type": "Number"
        }
      }
    }
  ]
}