{
  "argument_loc": "Unspecified",
  "description": "Gets the waypoint loiter altitude.",
  "effect_loc": "Unspecified",
  "examples": [
    "<sqf>private _loiterAlt = waypointLoiterAltitude [groupOne, 1];</sqf>"
  ],
  "groups": [
    "Waypoints"
  ],
  "id": "waypointLoiterAltitude",
  "name": "waypointLoiterAltitude",
  "problem_notes": [],
  "see_also": [
    "setWaypointLoiterAltitude"
  ],
  "status": "Passed",
  "syntax": [
    {
      "call": {
        "Unary": "waypoint"
      },
      "ret": {
        "type": "Number"
      },
      "right": {
        "Item": {
          "name": "waypoint",
          "type": "Waypoint"
        }
      }
    }
  ]
}